BlueDesc_pywrapper/__init__.py
BlueDesc_pywrapper/bluedesc_pywrapper.py
BlueDesc_pywrapper/descs.json
BlueDesc_pywrapper/dtypes.json
BlueDesc_pywrapper/utils.py
bluedesc_pywrapper-0.0.6.post1.dist-info/licenses/LICENSE
bluedesc_pywrapper-0.0.6.post1.dist-info/METADATA
bluedesc_pywrapper-0.0.6.post1.dist-info/WHEEL
bluedesc_pywrapper-0.0.6.post1.dist-info/top_level.txt
bluedesc_pywrapper-0.0.6.post1.dist-info/RECORD
